template_store/__init__.py
template_store/base_template_store.py
template_store/simple_template_store.py
template_store-0.1.0.dist-info/LICENSE
template_store-0.1.0.dist-info/WHEEL
template_store-0.1.0.dist-info/METADATA
template_store-0.1.0.dist-info/RECORD
