Metadata-Version: 2.1
Name: template-store
Version: 0.1.0
Summary: lumoz.ai brick templates store
License: MIT
Author: Attinad Software
Author-email: attinad@attinadsoftware.com
Requires-Python: >=3.6,<4.0
Classifier: License :: OSI Approved :: MIT License
Classifier: Programming Language :: Python :: 3
Classifier: Programming Language :: Python :: 3.6
Classifier: Programming Language :: Python :: 3.7
Classifier: Programming Language :: Python :: 3.8
Requires-Dist: grpcio
Requires-Dist: grpcio-tools
